topsis102203142/__init__.py
topsis102203142/topsis.py
Topsis102203142-0.1.dist-info/LICENSE
Topsis102203142-0.1.dist-info/METADATA
Topsis102203142-0.1.dist-info/WHEEL
Topsis102203142-0.1.dist-info/top_level.txt
Topsis102203142-0.1.dist-info/RECORD
